MANIFEST.in
README.md
setup.py
bin/shakky
shakky/__init__.py
shakky.egg-info/PKG-INFO
shakky.egg-info/SOURCES.txt
shakky.egg-info/dependency_links.txt
shakky.egg-info/requires.txt
shakky.egg-info/top_level.txt