Metadata-Version: 1.0
Name: shakky
Version: 0.0.5
Summary: shakky 是一个脚本（命令等）定时执行的 WebService 框架，它提供了 RestAPI 来帮助开发人员更容易的将脚本设置成一个定时任务。
Home-page: https://pypi.python.org/pypi?:action=display&name=shakky
Author: xiaoh
Author-email: xiaoh@about.me
License: MIT Licence
Keywords: xiaoh,xingming,shakky,crontab,service
Platform: any
